{
    "ClassName": "",
    "Include": "",
    "Chance": 1.0,
    "Quantity": {
        "Min": 0.0,
        "Max": 0.0
    },
    "Health": [],
    "InventoryAttachments": [
        {
            "SlotName": "Body",
            "Items": [
                {
                    "ClassName": "LeatherJacket_Black",
                    "Include": "",
                    "Chance": 1.0,
                    "Quantity": {
                        "Min": 0.0,
                        "Max": 0.0
                    },
                    "Health": [
                        {
                            "Min": 0.699999988079071,
                            "Max": 1.0,
                            "Zone": ""
                        }
                    ],
                    "InventoryAttachments": [],
                    "InventoryCargo": [],
                    "ConstructionPartsBuilt": [],
                    "Sets": []
                }
                
            ]
        },
		{
            "SlotName": "Vest",
            "Items": [
                {
                    "ClassName": "PlateCarrierVest",
                    "Include": "",
                    "Chance": 0.1,
                    "Quantity": {
                        "Min": 0.0,
                        "Max": 0.0
                    },
                    "Health": [
                        {
                            "Min": 0.699999988079071,
                            "Max": 1.0,
                            "Zone": ""
                        }
                    ],
                    "InventoryAttachments": [],
                    "InventoryCargo": [],
                    "ConstructionPartsBuilt": [],
                    "Sets": []
                }
                
                
            ]
        },
        {
            "SlotName": "Legs",
            "Items": [
				{
                    "ClassName": "Jeans_Black",
                    "Include": "",
                    "Chance": 1.0,
                    "Quantity": {
                        "Min": 0.0,
                        "Max": 0.0
                    },
                    "Health": [
                        {
                            "Min": 0.699999988079071,
                            "Max": 1.0,
                            "Zone": ""
                        }
                    ],
                    "InventoryAttachments": [],
                    "InventoryCargo": [],
                    "ConstructionPartsBuilt": [],
                    "Sets": []
                }
            ]
        },
        {
            "SlotName": "Feet",
            "Items": [
                {
                    "ClassName": "Wellies_Grey",
                    "Include": "",
                    "Chance": 1.0,
                    "Quantity": {
                        "Min": 0.0,
                        "Max": 0.0
                    },
                    "Health": [
                        {
                            "Min": 0.699999988079071,
                            "Max": 1.0,
                            "Zone": ""
                        }
                    ],
                    "InventoryAttachments": [],
                    "InventoryCargo": [],
                    "ConstructionPartsBuilt": [],
                    "Sets": []
                }
            ]
        },
        
        {
            "SlotName": "Headgear",
            "Items": [
                {
                    "ClassName": "CowboyHat_Black",
                    "Include": "",
                    "Chance": 1.0,
                    "Quantity": {
                        "Min": 0.0,
                        "Max": 0.0
                    },
                    "Health": [
                        {
                            "Min": 0.699999988079071,
                            "Max": 1.0,
                            "Zone": ""
                        }
                    ],
                    "InventoryAttachments": [],
                    "InventoryCargo": [],
                    "ConstructionPartsBuilt": [],
                    "Sets": []
				}
            ]
        },
        {
            "SlotName": "Gloves",
            "Items": [
                {
                    "ClassName": "LeatherGloves_Brown",
                    "Include": "",
                    "Chance": 0.5,
                    "Quantity": {
                        "Min": 0.0,
                        "Max": 0.0
                    },
                    "Health": [
                        {
                            "Min": 0.699999988079071,
                            "Max": 1.0,
                            "Zone": ""
                        }
                    ],
                    "InventoryAttachments": [],
                    "InventoryCargo": [],
                    "ConstructionPartsBuilt": [],
                    "Sets": []
                }
            ]
        }
		
    ],
    "InventoryCargo": [],
    "ConstructionPartsBuilt": [],
    "Sets": [
		{
            "ClassName": "WEAPON",
            "Include": "",
            "Chance": 1.0,
            "Quantity": {
                "Min": 0.0,
                "Max": 0.0
            },
            "Health": [],
            "InventoryAttachments": [
                {
                    "SlotName": "Shoulder",
                    "Items": [
                        {
                            "ClassName": "M16A2",
                            "Include": "",
                            "Chance": 1.0,
                            "Quantity": {
                                "Min": 0.0,
                                "Max": 0.0
                            },
                            "Health": [],
                            "InventoryAttachments": [
							{
                    "ClassName": "Mag_STANAG_60Rnd",
                    "Include": "",
                    "Chance": 1.0,
                    "Quantity": {
                        "Min": 0.0,
                        "Max": 0.0
                    },
                    "Health": [],
                    "InventoryAttachments": [],
                    "InventoryCargo": [],
                    "ConstructionPartsBuilt": [],
                    "Sets": []
                }
							],
                            "InventoryCargo": [],
                            "ConstructionPartsBuilt": [],
                            "Sets": []
                        }
                    ]
                }
            ],
            "InventoryCargo": [
                {
                    "ClassName": "Mag_STANAG_30Rnd",
                    "Include": "",
                    "Chance": 1.0,
                    "Quantity": {
                        "Min": 0.0,
                        "Max": 0.0
                    },
                    "Health": [],
                    "InventoryAttachments": [],
                    "InventoryCargo": [],
                    "ConstructionPartsBuilt": [],
                    "Sets": []
                },
				{
                    "ClassName": "Mag_STANAG_30Rnd",
                    "Include": "",
                    "Chance": 1.0,
                    "Quantity": {
                        "Min": 0.0,
                        "Max": 0.0
                    },
                    "Health": [],
                    "InventoryAttachments": [],
                    "InventoryCargo": [],
                    "ConstructionPartsBuilt": [],
                    "Sets": []
                }
                
            ],
            "ConstructionPartsBuilt": [],
            "Sets": []
        }
		  
        
    ]
}