{
    "ClassName": "",
    "Include": "",
    "Chance": 1.0,
    "Quantity": {
        "Min": 0.0,
        "Max": 0.0
    },
    "Health": [],
    "InventoryAttachments": [
        {
            "SlotName": "Body",
            "Items": [
                {
                    "ClassName": "LabCoat",
                    "Include": "",
                    "Chance": 1.0,
                    "Quantity": {
                        "Min": 0.0,
                        "Max": 0.0
                    },
                    "Health": [
                        {
                            "Min": 0.699999988079071,
                            "Max": 1.0,
                            "Zone": ""
                        }
                    ],
                    "InventoryAttachments": [],
                    "InventoryCargo": [],
                    "ConstructionPartsBuilt": [],
                    "Sets": []
                }
            ]
        },
		{
            "SlotName": "Vest",
            "Items": []
        },
		{
            "SlotName": "Eyewear",
            "Items": [
               {
                    "ClassName": "ThickFramesGlasses",
                    "Include": "",
                    "Chance": 1.0,
                    "Quantity": {
                        "Min": 0.0,
                        "Max": 0.0
                    },
                    "Health": [
                        {
                            "Min": 0.699999988079071,
                            "Max": 1.0,
                            "Zone": ""
                        }
                    ],
                    "InventoryAttachments": [],
                    "InventoryCargo": [],
                    "ConstructionPartsBuilt": [],
                    "Sets": []
                }
            ]
        },
		{
		    "SlotName": "Mask",
            "Items": []
        },
        {
            "SlotName": "Legs",
            "Items": [
                {
                    "ClassName": "MedicalScrubsPants_White",
                    "Include": "",
                    "Chance": 1.0,
                    "Quantity": {
                        "Min": 0.0,
                        "Max": 0.0
                    },
                    "Health": [
                        {
                            "Min": 0.699999988079071,
                            "Max": 1.0,
                            "Zone": ""
                        }
                    ],
                    "InventoryAttachments": [],
                    "InventoryCargo": [],
                    "ConstructionPartsBuilt": [],
                    "Sets": []
                }
            ]
        },
        {
            "SlotName": "Feet",
            "Items": [
			    {
                    "ClassName": "CombatBoots_Brown",
                    "Include": "",
                    "Chance": 1.0,
                    "Quantity": {
                        "Min": 0.0,
                        "Max": 0.0
                    },
                    "Health": [
                        {
                            "Min": 0.699999988079071,
                            "Max": 1.0,
                            "Zone": ""
                        }
                    ],
                    "InventoryAttachments": [],
                    "InventoryCargo": [],
                    "ConstructionPartsBuilt": [],
                    "Sets": []
                }
            ]
        },	
		{
            "SlotName": "Back",
            "Items": []
        },	
		{
            "SlotName": "Headgear",
            "Items": []
        },
        {
            "SlotName": "Gloves",
            "Items": []
        }
    ],
    "InventoryCargo": [],
    "ConstructionPartsBuilt": [],
    "Sets": [
		{
            "ClassName": "WEAPON",
            "Include": "",
            "Chance": 1.0,
            "Quantity": {
                "Min": 0.0,
                "Max": 0.0
            },
            "Health": [],
            "InventoryAttachments": [
                {
                    "SlotName": "Hands",
                    "Items": [
                        {
                            "ClassName": "Expansion_M9",
                            "Include": "",
                            "Chance": 1.0,
                            "Quantity": {
                                "Min": 0.0,
                                "Max": 0.0
                            },
                            "Health": [],
                            "InventoryAttachments": [
                                {
                                    "SlotName": "",
                                    "Items": [
                                        {
                                            "ClassName": "Mag_Expansion_M9_15Rnd",
                                            "Include": "",
                                            "Chance": 1.0,
                                            "Quantity": {
                                                "Min": 0.0,
                                                "Max": 0.0
                                            },
                                            "Health": [],
                                            "InventoryAttachments": [],
                                            "InventoryCargo": [],
                                            "ConstructionPartsBuilt": [],
                                            "Sets": []
                                        }
                                    ]
                                }
                            ],
                            "InventoryCargo": [],
                            "ConstructionPartsBuilt": [],
                            "Sets": []
                        }
                    ]
                }
            ],
            "InventoryCargo": [
                {
                    "ClassName": "Mag_Expansion_M9_15Rnd",
                    "Include": "",
                    "Chance": 1.0,
                    "Quantity": {
                        "Min": 0.0,
                        "Max": 0.0
                    },
                    "Health": [],
                    "InventoryAttachments": [],
                    "InventoryCargo": [],
                    "ConstructionPartsBuilt": [],
                    "Sets": []
                },
                {
                    "ClassName": "Mag_Expansion_M9_15Rnd",
                    "Include": "",
                    "Chance": 0.15000000596046449,
                    "Quantity": {
                        "Min": 0.0,
                        "Max": 0.0
                    },
                    "Health": [],
                    "InventoryAttachments": [],
                    "InventoryCargo": [],
                    "ConstructionPartsBuilt": [],
                    "Sets": []
                }
            ],
            "ConstructionPartsBuilt": [],
            "Sets": []
        }
	]
}